prob_distributions_sb/Binomialdistribution.py
prob_distributions_sb/Gaussiandistribution.py
prob_distributions_sb/Generaldistribution.py
prob_distributions_sb/__init__.py
prob_distributions_sb-0.3.dist-info/METADATA
prob_distributions_sb-0.3.dist-info/WHEEL
prob_distributions_sb-0.3.dist-info/top_level.txt
prob_distributions_sb-0.3.dist-info/RECORD
