Metadata-Version: 2.1
Name: prob-distributions-sb
Version: 0.3
Summary: Gaussian, Binomial distributions
Home-page: UNKNOWN
Author: Spurthi Bollina
Author-email: bollinaspurthi@gmail.com
License: UNKNOWN
Platform: UNKNOWN
